hy_sicp/__init__.py
hy_sicp/hy_sicp.py
hy_sicp-0.0.1.dist-info/AUTHORS.rst
hy_sicp-0.0.1.dist-info/LICENSE
hy_sicp-0.0.1.dist-info/METADATA
hy_sicp-0.0.1.dist-info/WHEEL
hy_sicp-0.0.1.dist-info/top_level.txt
hy_sicp-0.0.1.dist-info/RECORD
