Metadata-Version: 2.1
Name: hy-sicp
Version: 0.0.1
Summary: SICP in hy
Home-page: https://github.com/mkirchner/hy_sicp
Author: Marc Kirchner
Author-email: mail@marc-kirchner.de
License: MIT license
Keywords: hy_sicp
Platform: UNKNOWN
Classifier: Development Status :: 2 - Pre-Alpha
Classifier: Intended Audience :: Developers
Classifier: License :: OSI Approved :: MIT License
Classifier: Natural Language :: English
Classifier: Programming Language :: Python :: 3
Classifier: Programming Language :: Python :: 3.5
Classifier: Programming Language :: Python :: 3.6
Classifier: Programming Language :: Python :: 3.7
Classifier: Programming Language :: Python :: 3.8
Requires-Python: >=3.5
